aws_v4signer/__init__.py
aws_v4signer/aws_v4signer.py
aws_v4signer-0.7.dist-info/LICENSE
aws_v4signer-0.7.dist-info/METADATA
aws_v4signer-0.7.dist-info/WHEEL
aws_v4signer-0.7.dist-info/top_level.txt
aws_v4signer-0.7.dist-info/RECORD
