Metadata-Version: 2.1
Name: aws-v4signer
Version: 0.7
Summary: A python class to get the headers needed for v4 signing an AWS request
Home-page: https://github.com/gridsmartercities/aws-v4signer
Author: Grid Smarter Cities
Author-email: open-source@gridsmartercities.com
License: MIT
Keywords: aws python v4 signature
Platform: UNKNOWN
Classifier: Intended Audience :: Developers
Classifier: Development Status :: 3 - Alpha
Classifier: Programming Language :: Python :: 3
Classifier: License :: OSI Approved :: MIT License
Classifier: Operating System :: OS Independent
Classifier: Natural Language :: English
License-File: LICENSE
